sotempmail/__init__.py
sotempmail-0.1.3.dist-info/LICENSE
sotempmail-0.1.3.dist-info/METADATA
sotempmail-0.1.3.dist-info/WHEEL
sotempmail-0.1.3.dist-info/RECORD
