Metadata-Version: 2.3
Name: sotempmail
Version: 0.1.3
Summary: Simple wrapper for tempmail.so api.
License: MIT
Author: João B. Santos
Author-email: joaobatista.sf@hotmail.com
Requires-Python: >=3.9
Classifier: License :: OSI Approved :: MIT License
Classifier: Programming Language :: Python :: 3
Classifier: Programming Language :: Python :: 3.9
Classifier: Programming Language :: Python :: 3.10
Classifier: Programming Language :: Python :: 3.11
Classifier: Programming Language :: Python :: 3.12
Classifier: Programming Language :: Python :: 3.13
Requires-Dist: aiohttp (>=3.12.13,<4.0.0)
Project-URL: Homepage, https://github.com/jbsanf/sotempmail
